setup.py
funniest/__init__.py
funniest_pan.egg-info/PKG-INFO
funniest_pan.egg-info/SOURCES.txt
funniest_pan.egg-info/dependency_links.txt
funniest_pan.egg-info/not-zip-safe
funniest_pan.egg-info/top_level.txt