Metadata-Version: 1.0
Name: funniest-pan
Version: 0.1
Summary: The funniest joke in the world adapted by Pan
Home-page: http://github.com/panc/funniest_pan
Author: panc
Author-email: panc@example.com
License: Purdue
Platform: UNKNOWN
